{"set": "SOS", "id": "2f6b3fbf60", "rank": "diamond", "record": "7-1", "drafted": "2026-05-19", "picks": [{"pack": 0, "pick": 0, "cards": ["Arnyn, Deathbloom Botanist", "Burrog Banemaker", "Chase Inspiration", "Fractal Anomaly", "Interjection", "Mage Tower Referee", "Mind Roots", "Monstrous Rage", "Pterafractyl", "Shattered Sanctum", "Shopkeeper's Bane", "Skycoach Waypoint", "Spectacle Summit", "Strife Scholar"], "picked": "Monstrous Rage", "maindecked": false}, {"pack": 0, "pick": 1, "cards": ["Burrog Banemaker", "End of the Hunt", "Growth Curve", "Inkshape Demonstrator", "Killian's Confidence", "Knockout Maneuver", "Orysa, Tide Choreographer", "Owlin Historian", "Paradox Gardens", "Procrastinate", "Spirit Mascot", "Stone Docent", "Strife Scholar"], "picked": "Inkshape Demonstrator", "maindecked": true}, {"pack": 0, "pick": 2, "cards": ["Burrog Banemaker", "Eager Glyphmage", "Forum of Amity", "Fractal Anomaly", "Noxious Newt", "Page, Loose Leaf", "Quick Study", "Rearing Embermare", "Requisition Raid", "Silverquill Charm", "Ulna Alley Shopkeep", "Wild Hypothesis"], "picked": "Silverquill Charm", "maindecked": true}, {"pack": 0, "pick": 3, "cards": ["Diary of Dreams", "Noxious Newt", "Pull from the Grave", "Quick Study", "Root Manipulation", "Rubble Rouser", "Sanar, Unfinished Genius", "Soaring Stoneglider", "Stargaze", "Stirring Honormancer", "Swamp"], "picked": "Stirring Honormancer", "maindecked": true}, {"pack": 0, "pick": 4, "cards": ["Campus Composer", "Essenceknit Scholar", "Follow the Lumarets", "Forest", "Grapple with Death", "Heated Argument", "Honorbound Page", "Lluwen, Exchange Student", "Muse's Encouragement", "Pongify"], "picked": "Grapple with Death", "maindecked": false}, {"pack": 0, "pick": 5, "cards": ["Burrog Banemaker", "Essence Scatter", "Interjection", "Mountain", "Owlin Historian", "Pursue the Past", "Quandrix Charm", "Silverquill Charm", "Sleight of Hand"], "picked": "Silverquill Charm", "maindecked": true}, {"pack": 0, "pick": 6, "cards": ["Biblioplex Tomekeeper", "Disdainful Stroke", "Embrace the Paradox", "Fields of Strife", "Procrastinate", "Scathing Shadelock", "Tackle Artist", "Zimone's Experiment"], "picked": "Scathing Shadelock", "maindecked": false}, {"pack": 0, "pick": 7, "cards": ["Feed the Swarm", "Flow State", "Glorious Decay", "Goblin Glasswright", "Imperious Inkmage", "Island", "Page, Loose Leaf"], "picked": "Imperious Inkmage", "maindecked": true}, {"pack": 0, "pick": 8, "cards": ["Burrog Banemaker", "Chase Inspiration", "Fractal Anomaly", "Mage Tower Referee", "Shopkeeper's Bane", "Skycoach Waypoint"], "picked": "Burrog Banemaker", "maindecked": true}, {"pack": 0, "pick": 9, "cards": ["Killian's Confidence", "Knockout Maneuver", "Orysa, Tide Choreographer", "Procrastinate", "Strife Scholar"], "picked": "Killian's Confidence", "maindecked": true}, {"pack": 0, "pick": 10, "cards": ["Fractal Anomaly", "Page, Loose Leaf", "Rearing Embermare", "Ulna Alley Shopkeep"], "picked": "Fractal Anomaly", "maindecked": false}, {"pack": 0, "pick": 11, "cards": ["Diary of Dreams", "Stargaze", "Swamp"], "picked": "Diary of Dreams", "maindecked": true}, {"pack": 0, "pick": 12, "cards": ["Forest", "Honorbound Page"], "picked": "Honorbound Page", "maindecked": true}, {"pack": 0, "pick": 13, "cards": ["Mountain"], "picked": "Mountain", "maindecked": false}, {"pack": 1, "pick": 0, "cards": ["Abigale, Poet Laureate", "Applied Geometry", "Bogwater Lumaret", "Cyclonic Rift", "Daydream", "Deluge Virtuoso", "Forum of Amity", "Growth Curve", "Noxious Newt", "Rehearsed Debater", "Render Speechless", "Rubble Rouser", "Sneering Shadewriter", "Witherbloom Charm"], "picked": "Render Speechless", "maindecked": true}, {"pack": 1, "pick": 1, "cards": ["Arcane Omens", "Diary of Dreams", "Flashback", "Forest", "Garrison Excavator", "Grapple with Death", "Interjection", "Pest Mascot", "Procrastinate", "Return the Favor", "Social Snub", "Strife Scholar", "Thunderdrum Soloist"], "picked": "Interjection", "maindecked": false}, {"pack": 1, "pick": 2, "cards": ["Bitter Triumph", "Burrog Banemaker", "Burrog Barrage", "Charging Strifeknight", "Eager Glyphmage", "Elemental Mascot", "Expressive Firedancer", "Quick Study", "Rancorous Archaic", "Scolding Administrator", "Snarl Song", "Titan's Grave"], "picked": "Scolding Administrator", "maindecked": true}, {"pack": 1, "pick": 3, "cards": ["Brush Off", "Choreographed Sparks", "Cost of Brilliance", "Embrace the Paradox", "Emil, Vastlands Roamer", "Fields of Strife", "Interjection", "Muse's Encouragement", "Pursue the Past", "Shared Roots", "Shopkeeper's Bane"], "picked": "Cost of Brilliance", "maindecked": true}, {"pack": 1, "pick": 4, "cards": ["Homesickness", "Honorbound Page", "Oracle's Restoration", "Plains", "Procrastinate", "Pull from the Grave", "Rancorous Archaic", "Spirit Mascot", "Topiary Lecturer", "Wilt in the Heat"], "picked": "Wilt in the Heat", "maindecked": false}, {"pack": 1, "pick": 5, "cards": ["Cost of Brilliance", "Hungry Graffalon", "Lecturing Scornmage", "Locust Spray", "Plains", "Pterafractyl", "Scolding Administrator", "Spiritcall Enthusiast", "Zimone's Experiment"], "picked": "Scolding Administrator", "maindecked": true}, {"pack": 1, "pick": 6, "cards": ["Campus Composer", "Cheerful Osteomancer", "Dig Site Inventory", "Muse's Encouragement", "Potioner's Trove", "Root Manipulation", "Titan's Grave", "Wild Hypothesis"], "picked": "Dig Site Inventory", "maindecked": true}, {"pack": 1, "pick": 7, "cards": ["Follow the Lumarets", "Matterbending Mage", "Pursue the Past", "Snooping Page", "Social Snub", "Zealous Lorecaster", "Zimone's Experiment"], "picked": "Snooping Page", "maindecked": true}, {"pack": 1, "pick": 8, "cards": ["Abigale, Poet Laureate", "Deluge Virtuoso", "Growth Curve", "Noxious Newt", "Rehearsed Debater", "Sneering Shadewriter"], "picked": "Abigale, Poet Laureate", "maindecked": true}, {"pack": 1, "pick": 9, "cards": ["Forest", "Procrastinate", "Return the Favor", "Social Snub", "Strife Scholar"], "picked": "Social Snub", "maindecked": false}, {"pack": 1, "pick": 10, "cards": ["Eager Glyphmage", "Elemental Mascot", "Quick Study", "Rancorous Archaic"], "picked": "Eager Glyphmage", "maindecked": true}, {"pack": 1, "pick": 11, "cards": ["Embrace the Paradox", "Interjection", "Muse's Encouragement"], "picked": "Embrace the Paradox", "maindecked": false}, {"pack": 1, "pick": 12, "cards": ["Plains", "Procrastinate"], "picked": "Procrastinate", "maindecked": false}, {"pack": 1, "pick": 13, "cards": ["Plains"], "picked": "Plains", "maindecked": false}, {"pack": 2, "pick": 0, "cards": ["Brush Off", "Essence Scatter", "Essenceknit Scholar", "Fractal Mascot", "Goblin Glasswright", "Hardened Academic", "Killian's Confidence", "Landscape Painter", "Prismari, the Inspiration", "Pursue the Past", "Spell Pierce", "Stress Dream", "Swamp", "Wilt in the Heat"], "picked": "Hardened Academic", "maindecked": false}, {"pack": 2, "pick": 1, "cards": ["Aberrant Manawurm", "Bitter Triumph", "Eager Glyphmage", "Homesickness", "Hydro-Channeler", "Masterful Flourish", "Mountain", "Pest Mascot", "Pursue the Past", "Shopkeeper's Bane", "Stormcarved Coast", "Sundering Archaic", "Witherbloom Charm"], "picked": "Bitter Triumph", "maindecked": true}, {"pack": 2, "pick": 2, "cards": ["Biblioplex Tomekeeper", "Blazing Firesinger", "Bogwater Lumaret", "Cheerful Osteomancer", "Deluge Virtuoso", "Elite Interceptor", "Island", "Poisoner's Apprentice", "Seize the Spoils", "Snarl Song", "Teacher's Pest", "Tenured Concocter"], "picked": "Elite Interceptor", "maindecked": true}, {"pack": 2, "pick": 3, "cards": ["Cheerful Osteomancer", "Deluge Virtuoso", "Fields of Strife", "Garrison Excavator", "Helping Hand", "Hydro-Channeler", "Interjection", "Mind Roots", "Noxious Newt", "Strife Scholar", "Zealous Lorecaster"], "picked": "Helping Hand", "maindecked": false}, {"pack": 2, "pick": 4, "cards": ["Biblioplex Tomekeeper", "Chase Inspiration", "Dissection Practice", "Hungry Graffalon", "Island", "Kirol, History Buff", "Masterful Flourish", "Mind Roots", "Shopkeeper's Bane", "Zombify"], "picked": "Dissection Practice", "maindecked": true}, {"pack": 2, "pick": 5, "cards": ["Harsh Annotation", "Honorbound Page", "Inkling Mascot", "Old-Growth Educator", "Quick Study", "Rearing Embermare", "Rehearsed Debater", "Swamp", "Visionary's Dance"], "picked": "Inkling Mascot", "maindecked": true}, {"pack": 2, "pick": 6, "cards": ["Aberrant Manawurm", "Elemental Mascot", "Follow the Lumarets", "Fractal Mascot", "Lluwen, Exchange Student", "Owlin Historian", "Tablet of Discovery", "Ulna Alley Shopkeep"], "picked": "Owlin Historian", "maindecked": false}, {"pack": 2, "pick": 7, "cards": ["Borrowed Knowledge", "Quick Study", "Shattered Acolyte", "Stadium Tidalmage", "Tenured Concocter", "Unsubtle Mockery", "Zimone's Experiment"], "picked": "Shattered Acolyte", "maindecked": true}, {"pack": 2, "pick": 8, "cards": ["Fractal Mascot", "Killian's Confidence", "Landscape Painter", "Pursue the Past", "Spell Pierce", "Swamp"], "picked": "Killian's Confidence", "maindecked": false}, {"pack": 2, "pick": 9, "cards": ["Homesickness", "Masterful Flourish", "Mountain", "Shopkeeper's Bane", "Witherbloom Charm"], "picked": "Masterful Flourish", "maindecked": true}, {"pack": 2, "pick": 10, "cards": ["Biblioplex Tomekeeper", "Bogwater Lumaret", "Island", "Tenured Concocter"], "picked": "Bogwater Lumaret", "maindecked": false}, {"pack": 2, "pick": 11, "cards": ["Cheerful Osteomancer", "Interjection", "Strife Scholar"], "picked": "Cheerful Osteomancer", "maindecked": false}, {"pack": 2, "pick": 12, "cards": ["Biblioplex Tomekeeper", "Island"], "picked": "Biblioplex Tomekeeper", "maindecked": false}, {"pack": 2, "pick": 13, "cards": ["Swamp"], "picked": "Swamp", "maindecked": false}], "deck": ["Abigale, Poet Laureate", "Bitter Triumph", "Burrog Banemaker", "Cost of Brilliance", "Diary of Dreams", "Dig Site Inventory", "Dissection Practice", "Eager Glyphmage", "Elite Interceptor", "Honorbound Page", "Imperious Inkmage", "Inkling Mascot", "Inkshape Demonstrator", "Killian's Confidence", "Masterful Flourish", "Render Speechless", "Scolding Administrator", "Scolding Administrator", "Shattered Acolyte", "Silverquill Charm", "Silverquill Charm", "Snooping Page", "Stirring Honormancer"], "date": "2026-05-20"}